__init__.py
baekjoon_judge.py
judge.py
algorithm_problem/__init__.py
algorithm_problem/judge.py
baekjoon_judge/__init__.py
baekjoon_judge/baekjoon_judge.py
baekjoon_judge/judge.py
example_package/__init__.py
example_package/example.py
problem_solving_offline_judge/__init__.py
problem_solving_offline_judge/judge.py
problem_solving_offline_judge-1.0.0.dist-info/LICENSE
problem_solving_offline_judge-1.0.0.dist-info/METADATA
problem_solving_offline_judge-1.0.0.dist-info/WHEEL
problem_solving_offline_judge-1.0.0.dist-info/top_level.txt
problem_solving_offline_judge-1.0.0.dist-info/RECORD
