Metadata-Version: 2.1
Name: problem-solving-offline-judge
Version: 1.0.0
Summary: 알고리즘 문제풀이 오프라인 저지
Home-page: https://github.com/jihunleekr/problem_solving_offline_judge_python
Author: Jihun Lee
Author-email: zkoong21@gmail.com
License: UNKNOWN
Project-URL: Bug Tracker, https://github.com/jihunleekr/problem_solving_offline_judge_python/issues
Platform: UNKNOWN
Classifier: Programming Language :: Python :: 3
Classifier: License :: OSI Approved :: MIT License
Classifier: Operating System :: OS Independent
Requires-Python: >=3.6
License-File: LICENSE
Requires-Dist: colorama
